regressionSimHibou/__init__.py
regressionSimHibou/regressionSimHibou.py
regressionSimHibou-1.0.0.dist-info/LICENSE.txt
regressionSimHibou-1.0.0.dist-info/METADATA
regressionSimHibou-1.0.0.dist-info/WHEEL
regressionSimHibou-1.0.0.dist-info/top_level.txt
regressionSimHibou-1.0.0.dist-info/RECORD
