Metadata-Version: 2.1
Name: regressionSimHibou
Version: 1.0.0
Summary: An awesome package that does something useful.
Home-page: https://github.com/votre-repo/regressionSimHibou
Author: HibetElrahmane
Author-email: he.ouchene@esi-sba.dz
License: MIT
License-File: LICENSE.txt
Requires-Dist: numpy
Requires-Dist: pandas
